MANIFEST.in
README.md
requirements.txt
setup.cfg
setup.py
exhal/__init__.py
exhal/__main__.py
exhal/breathe.py
exhal/daemon.py
exhal/service.py
exhal/settings.yml
exhal.egg-info/PKG-INFO
exhal.egg-info/SOURCES.txt
exhal.egg-info/dependency_links.txt
exhal.egg-info/requires.txt
exhal.egg-info/top_level.txt
exhal.egg-info/zip-safe
scripts/exhal