Metadata-Version: 2.1
Name: exhal
Version: 1.1.0
Summary: Exhal for BlinkStick: Humanize your hardware
Home-page: https://github.com/nficano/exhal
Author: Nick Ficano
Author-email: nficano@gmail.com
License: MIT
Platform: UNKNOWN
Classifier: License :: OSI Approved :: MIT License
Classifier: Programming Language :: Python
Classifier: Programming Language :: Python :: 3.5
Classifier: Programming Language :: Python :: 3.6
Classifier: Programming Language :: Python :: 3.7
Classifier: Programming Language :: Python :: Implementation :: CPython
Classifier: Programming Language :: Python :: Implementation :: PyPy
